isq/__init__.py
isq/config.py
isq/errors.py
isq/globalVar.py
isq/mapping.py
isq/qpu.py
isq/quantum.py
isq/compile/QSyn.py
isq/compile/Simplify.py
isq/compile/__init__.py
isq/compile/matlab_gsvd.py
isq/compile/parser.py
isq/compile/parsetab.py
isq/compile/passes.py
isq/compile/qtypes.py
isq/compile/tokrules.py
isq/compile/tools.py
isq/device/__init__.py
isq/device/device.py
isq/device/grad.py
isq/device/task.py
isq/device/translate.py
isq/draw/__init__.py
isq/draw/drawer.py
isq/simulate/__init__.py
isq/simulate/operation.py
isq/simulate/simulator.py
isqopen-1.0.5.dist-info/METADATA
isqopen-1.0.5.dist-info/WHEEL
isqopen-1.0.5.dist-info/top_level.txt
isqopen-1.0.5.dist-info/RECORD
