Metadata-Version: 2.1
Name: isqopen
Version: 1.0.5
Summary: isq quantum kernel
Author: Lou Huazhe
Author-email: louhz@arclightquantum.com
Platform: python 3.8+
Requires-Dist: numpy (>=1.21.3)
Requires-Dist: ply (>=3.11)
Requires-Dist: scipy (>=1.7.1)
Requires-Dist: autograd
